Metadata-Version: 2.1
Name: write2list
Version: 1.1
Summary: Convert a tuple of lists to a list.
Home-page: https://github.com/janpreet/write2list
Author: Janpreet Singh
Author-email: janpreetsinghgill@gmail.com
License: UNKNOWN
Platform: UNKNOWN
Classifier: Programming Language :: Python :: 3
Classifier: License :: OSI Approved :: MIT License
Classifier: Operating System :: OS Independent
Requires-Python: >=2.7
